cascade_node_sdk/__init__.py
cascade_node_sdk/agent.py
cascade_node_sdk/cli_proxy.py
cascade_node_sdk/protobuffs/cascade_pb2.py
cascade_node_sdk/validation.py
cascade_node_sdk-0.1.0.dist-info/METADATA
cascade_node_sdk-0.1.0.dist-info/WHEEL
cascade_node_sdk-0.1.0.dist-info/entry_points.txt
cascade_node_sdk-0.1.0.dist-info/RECORD
