Metadata-Version: 2.1
Name: cascade_node_sdk
Version: 0.1.0
Summary: 
Author: Cody Hartsook
Author-email: chartsoo@cisco.com
Requires-Python: >=3.11,<3.12
Classifier: Programming Language :: Python :: 3
Classifier: Programming Language :: Python :: 3.11
Requires-Dist: click (>=8.1.7,<9.0.0)
Requires-Dist: flask-cors (>=4.0.0,<5.0.0)
Requires-Dist: grpcio (>=1.59.2,<2.0.0)
Requires-Dist: langchain (>=0.1.6,<0.2.0)
Requires-Dist: langchain-core (==0.1.23)
Requires-Dist: langchain-openai (==0.0.4)
Requires-Dist: langchainhub (>=0.1.14,<0.2.0)
Requires-Dist: nats-py (>=2.6.0,<3.0.0)
Requires-Dist: nest-asyncio (>=1.6.0,<2.0.0)
Requires-Dist: protobuf (>=4.25.0,<5.0.0)
Requires-Dist: python-dotenv (==1.0.0)
Requires-Dist: requests (>=2.31.0,<3.0.0)
Requires-Dist: traceloop-sdk (>=0.13.3,<0.14.0)
